whalegamer_forecast_mcp/__init__.py
whalegamer_forecast_mcp-0.1.2.dist-info/WHEEL
whalegamer_forecast_mcp-0.1.2.dist-info/entry_points.txt
whalegamer_forecast_mcp-0.1.2.dist-info/METADATA
whalegamer_forecast_mcp-0.1.2.dist-info/RECORD
