Metadata-Version: 2.3
Name: whalegamer-forecast-mcp
Version: 0.1.2
Summary: A第三个版本，希望能用
Author: Jker
Author-email: Jker <2933385376@qq.com>
Requires-Dist: mcp[cli]>=1.13.1
Requires-Dist: pandas==2.2.2
Requires-Dist: numpy==1.26.4
Requires-Dist: matplotlib==3.9.0
Requires-Dist: prophet==1.1.7
Requires-Dist: scikit-learn==1.7.1
Requires-Python: >=3.13.3
